setup.py
zfx_mysql/__init__.py
zfx_mysql/增加_单条记录.py
zfx_mysql/增加_多条记录.py
zfx_mysql/执行SQL语句.py
zfx_mysql/断开数据库连接.py
zfx_mysql/更新_SQL语句条件.py
zfx_mysql/更新_指定字段空值填充.py
zfx_mysql/更新_清空字段数据.py
zfx_mysql/更新_清空数据表.py
zfx_mysql/更新_置字段所有数据为Null.py
zfx_mysql/更新_追加内容.py
zfx_mysql/查询_取所有表名.py
zfx_mysql/查询_唯一值数量.py
zfx_mysql/查询_字段值列表.py
zfx_mysql/查询_最后一条记录.py
zfx_mysql/查询_条件查找.py
zfx_mysql/查询_第一条记录.py
zfx_mysql/查询_获取列名.py
zfx_mysql/查询_表记录总数.py
zfx_mysql/查询_随机取出一条记录.py
zfx_mysql/连接数据库.py
zfx_mysql.egg-info/PKG-INFO
zfx_mysql.egg-info/SOURCES.txt
zfx_mysql.egg-info/dependency_links.txt
zfx_mysql.egg-info/requires.txt
zfx_mysql.egg-info/top_level.txt